{
    "users": [
        {
            "id": "0", 
            "name": "Tony", 
            "headImg":"",
            "mood":"",
            "passwd": "123456", 
            "email": "123456@qq.com", 
            "gender": "male", 
            "birth": "1981-1-1",
            "cart": [
                {
                    "title":"PEACECAKE T-SHIRT",
                    "price":326.00,
                    "color":"#2B2C2E",
                    "size":"XS",
                    "img":"https://a.icons8.com/pobZZrRj/AqOgMa/bg.png",
                    "num":1
                }
            ],
            "order":[
                {
                    "code":"t000000000001",
                    "time":"2018-11-11",
                    "status":"finished",
                    "total":326.00,
                    "title":"PEACECAKE T-SHIRT",
                    "price":326.00,
                    "color":"#2B2C2E",
                    "size":"XS",
                    "img":"https://a.icons8.com/pobZZrRj/AqOgMa/bg.png",
                    "num":1
                },
                {
                    "code":"t000000000002",
                    "time":"2018-12-11",
                    "status":"delivery",
                    "total":326.00,
                    "title":"WOOL- BLEND DUFFLE COAT",
                    "price":326.00,
                    "color":"#D5C7BD",
                    "size":"M",
                    "img":"https://a.icons8.com/pobZZrRj/UWkp16/bitmap.png",
                    "num":1
                }
            ]
        }, 
        {
            "id": "1", 
            "name": "Gem", 
            "headImg":"",
            "mood":"",
            "passwd": "123456", 
            "email": "123456@163.com", 
            "gender": "female", 
            "birth": "1983-12-21",
            "cart":[],
            "order":[]
        }, 
        {
            "id": "2", 
            "name": "Tom",
            "headImg":"", 
            "mood":"",
            "passwd": "123456", 
            "email": "123456@yoho.com", 
            "gender": "male", 
            "birth": "1991-5-4",
            "cart":[
                {
                    "title":"PEACECAKE T-SHIRT",
                    "price":326.00,
                    "color":"#2B2C2E",
                    "size":"XXL",
                    "img": "https://a.icons8.com/pobZZrRj/AqOgMa/bg.png",
                    "num":1
                },
                {
                    "title":"WOOL- BLEND DUFFLE COAT",
                    "price":326.00,
                    "color":"#D5C7BD",
                    "size":"M",
                    "img":"https://a.icons8.com/pobZZrRj/UWkp16/bitmap.png",
                    "num":1
                }
            ],
            "order":[
                {
                    "code":"t000000000000",
                    "time":"2018-12-10",
                    "status":"received",
                    "total":326.00,
                    "title":"PEACECAKE T-SHIRT",
                    "price":326.00,
                    "color":"#2B2C2E",
                    "size":"XS",
                    "img":"https://a.icons8.com/pobZZrRj/AqOgMa/bg.png",
                    "num":1
                }
            ]
        }, 
        {
            "id": "3", 
            "name": "Kate", 
            "headImg":"",
            "mood":"",
            "passwd": "123456", 
            "email": "123456@sina.com", 
            "gender": "female", 
            "birth": "2001-12-31",
            "cart":[],
            "order":[
                {
                    "code":"k00000000001",
                    "time":"2018-11-01",
                    "status":"evaluation",
                    "total":326.00,
                    "title":"PEACECAKE T-SHIRT",
                    "price":326.00,
                    "color":"#2B2C2E",
                    "size":"XS",
                    "img":"https://a.icons8.com/pobZZrRj/AqOgMa/bg.png",
                    "num":1
                }
            ]
        }
    ], 
    "commodities": [
        {
            "type": "Shop", 
            "ad": "https://a.icons8.com/mYeXnhUP/ETtvuG/bitmap.png", 
            "content": [
                {
                    "name": "Female", 
                    "img": "https://a.icons8.com/mYeXnhUP/DFeUth/image.png"
                }, 
                {
                    "name": "Male", 
                    "img": "https://a.icons8.com/mYeXnhUP/M9zV5I/image.png"
                }, 
                {
                    "name": "Kids", 
                    "img": "https://a.icons8.com/mYeXnhUP/BI71V0/image.png"
                }
            ]
        }, 
        {
            "type": "Male", 
            "ad": "https://a.icons8.com/pobZZrRj/qUgsSo/image.png", 
            "content": [
                {
                    "name": "Clothes", 
                    "img": "https://a.icons8.com/mYeXnhUP/tYqNJx/image.png"
                }, 
                {
                    "name": "Shoes", 
                    "img": "https://a.icons8.com/bqjeoZSk/7UPNcv/image.png"
                }, 
                {
                    "name": "Pants", 
                    "img": "https://a.icons8.com/mYeXnhUP/UYfaua/image.png"
                }, 
                {
                    "name": "Ornaments", 
                    "img": "https://a.icons8.com/mYeXnhUP/KNC8a3/image.png"
                }, 
                {
                    "name": "Others", 
                    "img": ""
                }
            ]
        }, 
        {
            "type": "Female", 
            "ad": "https://a.icons8.com/pobZZrRj/PPHkAn/image.png", 
            "content": [
                {
                    "name": "Clothes", 
                    "img": "https://a.icons8.com/mYeXnhUP/JQgyfo/image.png"
                }, 
                {
                    "name": "Shoes", 
                    "img": "https://a.icons8.com/mYeXnhUP/Bi3ieF/image.png"
                }, 
                {
                    "name": "Pants", 
                    "img": "https://a.icons8.com/mYeXnhUP/6cg3mQ/image.png"
                }, 
                {
                    "name": "Ornaments", 
                    "img": "https://a.icons8.com/mYeXnhUP/ahzTiE/image.png"
                }, 
                {
                    "name": "Others", 
                    "img": ""
                }
            ]
        }, 
        {
            "type": "Kids", 
            "ad": "https://a.icons8.com/pobZZrRj/4jd3pb/image.png", 
            "content": [
                {
                    "name": "Clothes", 
                    "img": "https://a.icons8.com/pobZZrRj/sDA1Mr/image.png"
                }, 
                {
                    "name": "Shoes", 
                    "img": "https://a.icons8.com/pobZZrRj/WHLLxJ/image.png"
                }, 
                {
                    "name": "Pants", 
                    "img": "https://a.icons8.com/pobZZrRj/QcAC8N/image.png"
                }, 
                {
                    "name": "Ornaments", 
                    "img": "https://a.icons8.com/pobZZrRj/kRbCIu/image.png"
                }, 
                {
                    "name": "Others", 
                    "img": ""
                }
            ]
        }
    ], 
    "goods": [
        {
            "title": "PEACECAKE T-SHIRT",
            "name": "Clothes", 
            "describe": "Acne Studios’ Oscar jacket is a sleek, minimal take on a classic biker design.", 
            "type": "Male", 
            "discount": 450.99, 
            "price": 326.00, 
            "img": [
                "https://a.icons8.com/pobZZrRj/AqOgMa/bg.png"
            ], 
            "color": [
                "#2C334E", 
                "#4D4D4D", 
                "#2B2C2E", 
                "#493D37", 
                "#917052"
            ], 
            "size": [
                "XS", 
                "S", 
                "M", 
                "L", 
                "XL"
            ], 
            "detail": "1111111111"
        }, 
        {
            "title": "WOOL- BLEND DUFFLE COAT",
            "name": "Clothes", 
            "describe": "Acne Studios’ Oscar jacket is a sleek, minimal take on a classic biker design.", 
            "type": "Female", 
            "discount": 450.99, 
            "price": 326.00, 
            "img": [
                "https://a.icons8.com/pobZZrRj/UWkp16/bitmap.png"
            ], 
            "color": [
                "#C81C30", 
                "#B5C8D5", 
                "#48464C", 
                "#6A6476", 
                "#D5C7BD"
            ], 
            "size": [
                "XS", 
                "S", 
                "M", 
                "L", 
                "XL"
            ], 
            "detail": "222222222"
        }
    ]
}
